accompanist/__init__.py
accompanist/cmd_hear.py
accompanist/cmd_init.py
accompanist/cmd_listen.py
accompanist/cmd_play.py
accompanist/main.py
accompanist/utility.py
accompanist/version.py
accompanist/report/__init__.py
accompanist/report/draw_histgram.py
accompanist/report/draw_pie_chart.py
accompanist/report/draw_table.py
accompanist/report/write_comment.py
accompanist/report/write_front_cover.py
accompanist/report/write_header_footer.py
accompanist/resource/logo_trans.png
accompanist/resource/logo_trans_small.png
accompanist-1.3.3.dist-info/LICENSE
accompanist-1.3.3.dist-info/METADATA
accompanist-1.3.3.dist-info/WHEEL
accompanist-1.3.3.dist-info/entry_points.txt
accompanist-1.3.3.dist-info/top_level.txt
accompanist-1.3.3.dist-info/RECORD
