Metadata-Version: 2.1
Name: accompanist
Version: 1.3.3
Summary: Analysis AWS WAF logs and generate a report
Author: itsuki
License: MIT
License-File: LICENSE
Requires-Dist: click (>=8.1.3)
Requires-Dist: boto3 (>=1.26.126)
Requires-Dist: datetime (>=5.1)
Requires-Dist: pandas (>=2.0.1)
Requires-Dist: matplotlib (>=3.7.1)
Requires-Dist: PdfPages (>=0.1.0)
